elasticsearch6/__init__.py
elasticsearch6/compat.py
elasticsearch6/connection_pool.py
elasticsearch6/exceptions.py
elasticsearch6/serializer.py
elasticsearch6/transport.py
elasticsearch6/utils.py
elasticsearch6/client/__init__.py
elasticsearch6/client/cat.py
elasticsearch6/client/cluster.py
elasticsearch6/client/indices.py
elasticsearch6/client/ingest.py
elasticsearch6/client/nodes.py
elasticsearch6/client/remote.py
elasticsearch6/client/snapshot.py
elasticsearch6/client/tasks.py
elasticsearch6/client/utils.py
elasticsearch6/client/xpack/__init__.py
elasticsearch6/client/xpack/deprecation.py
elasticsearch6/client/xpack/graph.py
elasticsearch6/client/xpack/license.py
elasticsearch6/client/xpack/migration.py
elasticsearch6/client/xpack/ml.py
elasticsearch6/client/xpack/monitoring.py
elasticsearch6/client/xpack/security.py
elasticsearch6/client/xpack/watcher.py
elasticsearch6/connection/__init__.py
elasticsearch6/connection/base.py
elasticsearch6/connection/http_requests.py
elasticsearch6/connection/http_urllib3.py
elasticsearch6/connection/pooling.py
elasticsearch6/helpers/__init__.py
elasticsearch6/helpers/actions.py
elasticsearch6/helpers/errors.py
elasticsearch6/helpers/test.py
elasticsearch6-6.8.2.dist-info/AUTHORS
elasticsearch6-6.8.2.dist-info/LICENSE
elasticsearch6-6.8.2.dist-info/METADATA
elasticsearch6-6.8.2.dist-info/WHEEL
elasticsearch6-6.8.2.dist-info/top_level.txt
elasticsearch6-6.8.2.dist-info/RECORD
