Metadata-Version: 2.1
Name: elasticsearch6
Version: 6.8.2
Summary: Python client for Elasticsearch
Home-page: https://github.com/elastic/elasticsearch-py
Author: Honza Král, Nick Lang
Author-email: honza.kral@gmail.com, nick@nicklang.com
Maintainer: Seth Michael Larson
Maintainer-email: seth.larson@elastic.co
License: Apache-2.0
Platform: UNKNOWN
Classifier: Development Status :: 5 - Production/Stable
Classifier: License :: OSI Approved :: Apache Software License
Classifier: Intended Audience :: Developers
Classifier: Operating System :: OS Independent
Classifier: Programming Language :: Python
Classifier: Programming Language :: Python :: 2
Classifier: Programming Language :: Python :: 2.6
Classifier: Programming Language :: Python :: 2.7
Classifier: Programming Language :: Python :: 3
Classifier: Programming Language :: Python :: 3.2
Classifier: Programming Language :: Python :: 3.3
Classifier: Programming Language :: Python :: 3.4
Classifier: Programming Language :: Python :: 3.5
Classifier: Programming Language :: Python :: 3.6
Classifier: Programming Language :: Python :: Implementation :: CPython
Classifier: Programming Language :: Python :: Implementation :: PyPy
Requires-Python: >=2.6, !=3.0.*, !=3.1.*, !=3.2.*, <4
Provides-Extra: develop
Provides-Extra: requests
